bostaSDK/__init__.py
bostaSDK/apiClient/ApiClient.py
bostaSDK/apiClient/__init__.py
bostaSDK/business/Business.py
bostaSDK/business/__init__.py
bostaSDK/city/City.py
bostaSDK/city/__init__.py
bostaSDK/delivery/Delivery.py
bostaSDK/delivery/__init__.py
bostaSDK/delivery/create/CreateDeliveryRequest.py
bostaSDK/delivery/create/CreateDeliveryResponse.py
bostaSDK/delivery/create/__init__.py
bostaSDK/delivery/get/GetDeliveryDetailsRequest.py
bostaSDK/delivery/get/GetDeliveryDetailsResponse.py
bostaSDK/delivery/get/__init__.py
bostaSDK/delivery/list/ListAllDeliveriesRequest.py
bostaSDK/delivery/list/ListAllDeliveriesResponse.py
bostaSDK/delivery/list/__init__.py
bostaSDK/delivery/printAWB/PrintAWBRequest.py
bostaSDK/delivery/printAWB/PrintAWBResponse.py
bostaSDK/delivery/printAWB/__init__.py
bostaSDK/delivery/terminate/TerminateDeliveryRequest.py
bostaSDK/delivery/terminate/TerminateDeliveryResponse.py
bostaSDK/delivery/terminate/__init__.py
bostaSDK/delivery/track/TrackDeliveryRequest.py
bostaSDK/delivery/track/TrackDeliveryResponse.py
bostaSDK/delivery/track/__init__.py
bostaSDK/delivery/update/UpdateDeliveryRequest.py
bostaSDK/delivery/update/UpdateDeliveryResponse.py
bostaSDK/delivery/update/__init__.py
bostaSDK/pickup/Pickup.py
bostaSDK/pickup/__init__.py
bostaSDK/pickup/create/CreatePickupRequest.py
bostaSDK/pickup/create/CreatePickupResponse.py
bostaSDK/pickup/create/__init__.py
bostaSDK/pickup/delete/DeletePickupRequest.py
bostaSDK/pickup/delete/DeletePickupResponse.py
bostaSDK/pickup/delete/__init__.py
bostaSDK/pickup/get/GetPickupDetailsRequest.py
bostaSDK/pickup/get/GetPickupDetailsResponse.py
bostaSDK/pickup/get/__init__.py
bostaSDK/pickup/list/ListAllPickupsRequest.py
bostaSDK/pickup/list/ListAllPickupsResponse.py
bostaSDK/pickup/list/__init__.py
bostaSDK/pickup/update/UpdatePickupRequest.py
bostaSDK/pickup/update/UpdatePickupResponse.py
bostaSDK/pickup/update/__init__.py
bostaSDK/utils/Address.py
bostaSDK/utils/ContactPerson.py
bostaSDK-2.0.1.dist-info/LICENSE
bostaSDK-2.0.1.dist-info/METADATA
bostaSDK-2.0.1.dist-info/WHEEL
bostaSDK-2.0.1.dist-info/top_level.txt
bostaSDK-2.0.1.dist-info/RECORD
