Metadata-Version: 2.1
Name: bostaSDK
Version: 2.0.1
Summary: Bosta Python SDK
Home-page: https://pypi.org/project/bostaSDK/
Author: bosta
Author-email: sdk@bosta.com
License: LICENSE
Keywords: bosta,client-sdk,api,api-integration
Platform: UNKNOWN
Requires-Python: >=3.6
Requires-Dist: requests
